kedro_expectations/__init__.py
kedro_expectations/actions.py
kedro_expectations/constants.py
kedro_expectations/exceptions.py
kedro_expectations/kedro_expectations.py
kedro_expectations/notification.py
kedro_expectations/utils.py
kedro_expectations/assistant/__init__.py
kedro_expectations/assistant/categorical_columns_rule.json
kedro_expectations/assistant/column_value_nonnullity_rule.json
kedro_expectations/assistant/column_value_nullity_rule.json
kedro_expectations/assistant/column_value_uniqueness_rule.json
kedro_expectations/assistant/datetime_columns_rule.json
kedro_expectations/assistant/numeric_columns_rule.json
kedro_expectations/assistant/numeric_columns_rule_full.json
kedro_expectations/assistant/numeric_columns_rule_partitioned.json
kedro_expectations/assistant/rules.py
kedro_expectations/assistant/table_rule.json
kedro_expectations/assistant/table_rule_full.json
kedro_expectations/assistant/table_rule_partitioned.json
kedro_expectations/assistant/text_columns_rule.json
kedro_expectations/assistant/experimental/__init__.py
kedro_expectations/assistant/experimental/metric_repository/__init__.py
kedro_expectations/assistant/experimental/metric_repository/batch_inspector.py
kedro_expectations/assistant/experimental/metric_repository/cloud_data_store.py
kedro_expectations/assistant/experimental/metric_repository/data_store.py
kedro_expectations/assistant/experimental/metric_repository/metric_list_metric_retriever.py
kedro_expectations/assistant/experimental/metric_repository/metric_repository.py
kedro_expectations/assistant/experimental/metric_repository/metric_retriever.py
kedro_expectations/assistant/experimental/metric_repository/metrics.py
kedro_expectations/assistant/experimental/rule_based_profiler/__init__.py
kedro_expectations/assistant/experimental/rule_based_profiler/attributed_resolved_metrics.py
kedro_expectations/assistant/experimental/rule_based_profiler/builder.py
kedro_expectations/assistant/experimental/rule_based_profiler/exceptions.py
kedro_expectations-0.8.0.dist-info/licenses/LICENSE
kedro_expectations-0.8.0.dist-info/METADATA
kedro_expectations-0.8.0.dist-info/WHEEL
kedro_expectations-0.8.0.dist-info/entry_points.txt
kedro_expectations-0.8.0.dist-info/top_level.txt
kedro_expectations-0.8.0.dist-info/RECORD
