Metadata-Version: 2.4
Name: kedro-expectations
Version: 0.8.0
Summary: Combine Kedro data science pipelines with Great Expectations data validations.
Author-email: anacision GmbH <tech@anacision.de>
License: MIT
Classifier: License :: OSI Approved :: MIT License
Classifier: Programming Language :: Python :: 3.9
Classifier: Programming Language :: Python :: 3.10
License-File: LICENSE
Requires-Dist: great_expectations~=1.5.3
Requires-Dist: kedro-datasets~=2.0
Requires-Dist: kedro~=0.19
Requires-Dist: pandas~=2.1
Requires-Dist: s3fs~=2024.2.0
Requires-Dist: fsspec~=2024.2.0
Provides-Extra: dev
Requires-Dist: black>=23.0; extra == "dev"
Requires-Dist: twine~=4.0; extra == "dev"
Requires-Dist: gitflow-manager; extra == "dev"
Provides-Extra: test
Requires-Dist: pytest~=7.4; extra == "test"
Requires-Dist: pytest-cov~=5.0; extra == "test"
Requires-Dist: moto~=5.1.1; extra == "test"
Requires-Dist: flask~=3.1.0; extra == "test"
Requires-Dist: flask-cors~=5.0.1; extra == "test"
Dynamic: license-file
